numODEsolver/__init__.py
numODEsolver/solver.py
solver/__init__.py
solver/solver.py
numODEsolver-1.0.0.dist-info/LICENSE
numODEsolver-1.0.0.dist-info/METADATA
numODEsolver-1.0.0.dist-info/WHEEL
numODEsolver-1.0.0.dist-info/top_level.txt
numODEsolver-1.0.0.dist-info/RECORD
