Metadata-Version: 2.1
Name: numODEsolver
Version: 1.0.0
Summary: Tool that solves ODE's numerically. Written in Python.
Home-page: https://github.com/lukasnf/Numerical-ODE-Solver
Classifier: Programming Language :: Python :: 3
Classifier: License :: OSI Approved :: MIT License
Classifier: Operating System :: OS Independent
Requires-Python: >=3.8
License-File: LICENSE
Requires-Dist: numpy
Requires-Dist: sympy
Requires-Dist: scipy
